sedge/__init__.py
sedge/cli.py
sedge/engine.py
sedge/exceptions.py
sedge/keylib.py
sedge/sedge_template.conf
sedge/templates.py
sedge/urlhandling.py
sedge-2.3.1.dist-info/METADATA
sedge-2.3.1.dist-info/WHEEL
sedge-2.3.1.dist-info/entry_points.txt
sedge-2.3.1.dist-info/licenses/AUTHORS
sedge-2.3.1.dist-info/licenses/LICENSE
sedge-2.3.1.dist-info/RECORD
