Metadata-Version: 2.4
Name: sedge
Version: 2.3.1
Summary: Template and share OpenSSH ssh_config(5) files.
Author-email: Grahame Bowland <grahame@oreamnos.com.au>
License-File: AUTHORS
License-File: LICENSE
Classifier: Development Status :: 5 - Production/Stable
Classifier: Intended Audience :: System Administrators
Classifier: License :: OSI Approved :: GNU General Public License v3 (GPLv3)
Classifier: Operating System :: Microsoft :: Windows
Classifier: Operating System :: POSIX
Classifier: Topic :: System :: Networking
Requires-Python: <4,>=3.7
Requires-Dist: click
Requires-Dist: requests
